ao3_sync/__init__.py
ao3_sync/api/__init__.py
ao3_sync/api/client.py
ao3_sync/api/enums.py
ao3_sync/api/exceptions.py
ao3_sync/api/models.py
ao3_sync/api/resources/__init__.py
ao3_sync/api/resources/auth.py
ao3_sync/api/resources/bookmarks.py
ao3_sync/api/resources/series.py
ao3_sync/api/resources/works.py
ao3_sync/cli.py
ao3_sync/utils.py
ao3_sync-0.1.4.dist-info/METADATA
ao3_sync-0.1.4.dist-info/WHEEL
ao3_sync-0.1.4.dist-info/entry_points.txt
ao3_sync-0.1.4.dist-info/RECORD
